ppdet/__init__.py
ppdet/version.py
ppdet/core/__init__.py
ppdet/core/workspace.py
ppdet/core/config/__init__.py
ppdet/core/config/schema.py
ppdet/core/config/yaml_helpers.py
ppdet/data/__init__.py
ppdet/data/reader.py
ppdet/data/shm_utils.py
ppdet/data/utils.py
ppdet/data/source/__init__.py
ppdet/data/source/category.py
ppdet/data/source/coco.py
ppdet/data/source/dataset.py
ppdet/data/source/voc.py
ppdet/data/transform/__init__.py
ppdet/data/transform/autoaugment_utils.py
ppdet/data/transform/batch_operators.py
ppdet/data/transform/gridmask_utils.py
ppdet/data/transform/op_helper.py
ppdet/data/transform/operators.py
ppdet/engine/__init__.py
ppdet/engine/callbacks.py
ppdet/engine/env.py
ppdet/engine/export_utils.py
ppdet/engine/trainer.py
ppdet/engine/trainer_ssod.py
ppdet/metrics/__init__.py
ppdet/metrics/coco_utils.py
ppdet/metrics/json_results.py
ppdet/metrics/map_utils.py
ppdet/metrics/metrics.py
ppdet/model_zoo/MODEL_ZOO
ppdet/model_zoo/__init__.py
ppdet/model_zoo/model_zoo.py
ppdet/model_zoo/tests/__init__.py
ppdet/model_zoo/tests/test_get_model.py
ppdet/model_zoo/tests/test_list_model.py
ppdet/modeling/__init__.py
ppdet/modeling/bbox_utils.py
ppdet/modeling/initializer.py
ppdet/modeling/layers.py
ppdet/modeling/ops.py
ppdet/modeling/post_process.py
ppdet/modeling/shape_spec.py
ppdet/modeling/architectures/__init__.py
ppdet/modeling/architectures/detr.py
ppdet/modeling/architectures/meta_arch.py
ppdet/modeling/architectures/ppyoloe.py
ppdet/modeling/architectures/rtmdet.py
ppdet/modeling/architectures/yolo.py
ppdet/modeling/architectures/yolof.py
ppdet/modeling/architectures/yolov5.py
ppdet/modeling/architectures/yolov6.py
ppdet/modeling/architectures/yolov7.py
ppdet/modeling/architectures/yolov8.py
ppdet/modeling/architectures/yolox.py
ppdet/modeling/assigners/__init__.py
ppdet/modeling/assigners/atss_assigner.py
ppdet/modeling/assigners/simota_assigner.py
ppdet/modeling/assigners/task_aligned_assigner.py
ppdet/modeling/assigners/task_aligned_assigner_cr.py
py_sues-2.6.0.dist-info/LICENSE
py_sues-2.6.0.dist-info/METADATA
py_sues-2.6.0.dist-info/WHEEL
py_sues-2.6.0.dist-info/top_level.txt
py_sues-2.6.0.dist-info/RECORD
