Metadata-Version: 2.1
Name: py-sues
Version: 2.6.0
Summary: Object detection and instance segmentation toolkit based on PaddlePaddle
Home-page: https://github.com/PaddlePaddle/PaddleDetection
Download-URL: https://github.com/PaddlePaddle/PaddleDetection.git
Author: PaddlePaddle
License: Apache License 2.0
Keywords: ppdet paddle ppyolo
Classifier: Intended Audience :: Developers
Classifier: License :: OSI Approved :: Apache Software License
Classifier: Operating System :: OS Independent
Classifier: Natural Language :: Chinese (Simplified)
Classifier: Programming Language :: Python :: 3
Classifier: Programming Language :: Python :: 3.5
Classifier: Programming Language :: Python :: 3.6
Classifier: Programming Language :: Python :: 3.7
Classifier: Programming Language :: Python :: 3.8
Classifier: Topic :: Utilities
License-File: LICENSE
